{
  "id": "goat_brown",
  "name": "brown goat",
  "size": 64,
  "directions": [
    "south",
    "southwest",
    "west",
    "northwest",
    "north",
    "northeast",
    "east",
    "southeast"
  ],
  "generated_at": "2026-01-05T11:17:38.343Z",
  "generation_method": "reference_workflow",
  "notes": "South first, east with south ref, west flipped from east, others with south ref",
  "description": "brown goat, agile goat with beard, rectangular pupils, curved horns, domesticated farm animal, healthy well-fed appearance",
  "category": "animal",
  "original_description": "brown goat",
  "enriched_at": "2026-01-30T00:40:22.598Z"
}